flow/__init__.py
flow/__main__.py
flow/errors.py
flow/_internal/auth.py
flow/_internal/config.py
flow/_internal/config_loader.py
flow/_internal/data/__init__.py
flow/_internal/data/loaders.py
flow/_internal/data/mount_processor.py
flow/_internal/data/resolver.py
flow/_internal/frontends/__init__.py
flow/_internal/frontends/base.py
flow/_internal/frontends/registry.py
flow/_internal/frontends/cli/__init__.py
flow/_internal/frontends/cli/adapter.py
flow/_internal/frontends/slurm/__init__.py
flow/_internal/frontends/slurm/adapter.py
flow/_internal/frontends/slurm/converter.py
flow/_internal/frontends/slurm/parser.py
flow/_internal/frontends/submitit/__init__.py
flow/_internal/frontends/submitit/adapter.py
flow/_internal/frontends/yaml/__init__.py
flow/_internal/frontends/yaml/adapter.py
flow/_internal/init/__init__.py
flow/_internal/init/resolver.py
flow/_internal/init/validator.py
flow/_internal/init/writer.py
flow/_internal/integrations/__init__.py
flow/_internal/integrations/google_colab.py
flow/_internal/integrations/jupyter.py
flow/_internal/integrations/jupyter_persistence.py
flow/_internal/integrations/jupyter_session.py
flow/_internal/integrations/monarch.py
flow/_internal/integrations/monarch_adapter.py
flow/_internal/io/__init__.py
flow/_internal/io/http.py
flow/_internal/io/http_interfaces.py
flow/_internal/managers/__init__.py
flow/_internal/managers/task_manager.py
flow/_internal/storage/__init__.py
flow/_internal/storage/base.py
flow/_internal/storage/resolvers.py
flow/adapters/fcp_setup_adapter.py
flow/api/__init__.py
flow/api/client.py
flow/api/decorators.py
flow/api/dev.py
flow/api/health_models.py
flow/api/invoke.py
flow/api/models.py
flow/api/secrets.py
flow/bridge/__init__.py
flow/bridge/adapters.py
flow/bridge/base.py
flow/bridge/config.py
flow/bridge/fcp_api.py
flow/bridge/formatter.py
flow/bridge/http.py
flow/cli/__init__.py
flow/cli/__main__.py
flow/cli/app.py
flow/cli/main.py
flow/cli/provider_resolver.py
flow/cli/commands/README.md
flow_compute-2.1.0.dist-info/METADATA
flow_compute-2.1.0.dist-info/WHEEL
flow_compute-2.1.0.dist-info/entry_points.txt
flow_compute-2.1.0.dist-info/licenses/LICENSE.txt
flow_compute-2.1.0.dist-info/RECORD
