Metadata-Version: 2.4
Name: flow-compute
Version: 2.1.0
Summary: Simplified SDK for Foundry Compute Platform - GPU compute made simple
Project-URL: Homepage, https://github.com/foundrytechnologies/flow-v2
Project-URL: Documentation, https://github.com/foundrytechnologies/flow-v2
Project-URL: Repository, https://github.com/foundrytechnologies/flow-v2
Project-URL: Issues, https://github.com/foundrytechnologies/flow-v2/issues
Author-email: "Foundry Technologies, Inc." <support@mlfoundry.com>
License: Apache-2.0
License-File: LICENSE.txt
Keywords: ai,cloud,compute,foundry,gpu,ml
Classifier: Development Status :: 4 - Beta
Classifier: Intended Audience :: Developers
Classifier: License :: OSI Approved :: Apache Software License
Classifier: Programming Language :: Python :: 3
Classifier: Programming Language :: Python :: 3.10
Classifier: Programming Language :: Python :: 3.11
Classifier: Programming Language :: Python :: 3.12
Classifier: Programming Language :: Python :: 3.13
Classifier: Topic :: Scientific/Engineering :: Artificial Intelligence
Classifier: Topic :: Software Development :: Libraries :: Python Modules
Requires-Python: >=3.10
Requires-Dist: auto-click-auto>=0.1.5
Requires-Dist: boto3<2.0,>=1.26
Requires-Dist: click>=8.1.8
Requires-Dist: cloudpickle<4.0,>=2.0
Requires-Dist: dill<1.0,>=0.3.6
Requires-Dist: httpx<1.0,>=0.24.0
Requires-Dist: ipykernel<7.0,>=6.0
Requires-Dist: jinja2<4.0,>=3.0
Requires-Dist: jupyter-client<9.0,>=7.0
Requires-Dist: keyring<26.0,>=24.0
Requires-Dist: msgpack<2.0,>=1.0
Requires-Dist: paramiko<4.0,>=3.0
Requires-Dist: prompt-toolkit<4.0,>=3.0
Requires-Dist: pydantic<3.0,>=2.0
Requires-Dist: pyyaml<7.0,>=6.0
Requires-Dist: pyzmq<26.0,>=25.0
Requires-Dist: requests<3.0,>=2.31
Requires-Dist: rich<14.0,>=13.0
Provides-Extra: dev
Requires-Dist: black<25.0,>=23.0; extra == 'dev'
Requires-Dist: cloudpickle<4.0,>=2.0; extra == 'dev'
Requires-Dist: hypothesis<7.0,>=6.0; extra == 'dev'
Requires-Dist: moto<5.0,>=4.0; extra == 'dev'
Requires-Dist: mutmut<3.0,>=2.0; extra == 'dev'
Requires-Dist: mypy<2.0,>=1.0; extra == 'dev'
Requires-Dist: numpy>=1.20; extra == 'dev'
Requires-Dist: pexpect<5.0,>=4.8; extra == 'dev'
Requires-Dist: pytest-asyncio<1.0,>=0.21; extra == 'dev'
Requires-Dist: pytest-cov<6.0,>=4.0; extra == 'dev'
Requires-Dist: pytest-mock<4.0,>=3.0; extra == 'dev'
Requires-Dist: pytest-timeout<3.0,>=2.0; extra == 'dev'
Requires-Dist: pytest-xdist<4.0,>=3.0; extra == 'dev'
Requires-Dist: pytest<9.0,>=7.0; extra == 'dev'
Requires-Dist: radon<6.0,>=5.0; extra == 'dev'
Requires-Dist: responses<1.0,>=0.20; extra == 'dev'
Requires-Dist: ruff<1.0,>=0.1; extra == 'dev'
Requires-Dist: types-pyyaml; extra == 'dev'
Requires-Dist: types-requests; extra == 'dev'
Provides-Extra: recommended
Requires-Dist: numpy>=1.20; extra == 'recommended'
